rofetta/__init__.py
rofetta/__main__.py
rofetta/format_converters.py
rofetta/rofetta.py
rofetta/to_lp.py
rofetta/utils.py
rofetta/autoconv/__init__.py
rofetta/autoconv/autoconv.py
rofetta/autoconv/routines.py
test/__init__.py
test/test_convertion.py
rofetta-1.1.7.dist-info/METADATA
rofetta-1.1.7.dist-info/WHEEL
rofetta-1.1.7.dist-info/top_level.txt
rofetta-1.1.7.dist-info/RECORD
