Metadata-Version: 2.1
Name: rofetta
Version: 1.1.7
Summary: converter between the main FCA formats of formal contexts
Home-page: https://github.com/aluriak/rofetta
Author: Lucas Bourneuf
Author-email: lucas.bourneuf@laposte.net
License: GPL
Keywords: formal concept analysis,file format,convertion
Platform: UNKNOWN
Classifier: Development Status :: 4 - Beta
Classifier: Intended Audience :: Developers
Classifier: Programming Language :: Python :: 3
Classifier: Programming Language :: Python :: 3.6
Requires-Dist: pytest (>=3.1.2)
Requires-Dist: zest.releaser (==6.12.5)
Requires-Dist: graffunc (==0.2.2)
Requires-Dist: clyngor (>=0.3.20)
